<?xml version="1.0" encoding="UTF-8"?>
<!DOCTYPE suite SYSTEM "http://testng.org/testng-1.0.dtd">
<suite name="Suite" parallel="tests">
	<test name="Pixel_3_XL_API_28">
		<parameter name="emulator" value="true" />
		<parameter name="platformName" value="Android" />
		<parameter name="udid" value="emulator-5554" />
		<parameter name="deviceName" value="Pixel_3_XL_API_28" />
		<parameter name="systemPort" value="10001" />
		<parameter name="chromeDriverPort" value="11001" />
		<classes>
			<class name="com.Grizzly.runners.MobileRegressionRunner"></class>
		</classes>
	</test>
</suite>